ja_entity_parser-0.2.1.dist-info/licenses/LICENSE
ja_entityparser/__init__.py
ja_entityparser/normalizer.py
ja_entityparser/parser.py
ja_entityparser/dict/ja-entity-parser.dic
ja_entityparser/dict/normalize.json
ja_entityparser/dict/sudachi.json
ja_entity_parser-0.2.1.dist-info/METADATA
ja_entity_parser-0.2.1.dist-info/WHEEL
ja_entity_parser-0.2.1.dist-info/top_level.txt
ja_entity_parser-0.2.1.dist-info/RECORD
