Metadata-Version: 2.4
Name: ja-entity-parser
Version: 0.2.1
Summary: Japanese entity parser library for company/corporate name normalization and extraction.
Author: new-village
License:                                  Apache License
Project-URL: Homepage, https://github.com/new-village/ja-entity-parser
Requires-Python: >=3.8
License-File: LICENSE
Requires-Dist: sudachipy>=0.6.10
Requires-Dist: sudachidict-core>=20250515
Requires-Dist: joyokanji
Dynamic: license-file
